<?xml version="1.0" encoding="utf-8" ?>
<c2layout>
    <name>Fase2.2</name>
    <sid>269942504094085</sid>
    <event-sheet>Event Fase22</event-sheet>
    <size>
        <width>2880</width>
        <height>574</height>
    </size>
    <margins>
        <horizontal>500</horizontal>
        <vertical>500</vertical>
    </margins>
    <unbounded-scrolling>0</unbounded-scrolling>
    <layers>
        <layer name="Layer 0" sid="314666287799060">
            <initially-visible>1</initially-visible>
            <background-color>255,255,255</background-color>
            <transparent>0</transparent>
            <parallax>
                <x>1</x>
                <y>1</y>
            </parallax>
            <zoom-rate>1</zoom-rate>
            <opacity>1</opacity>
            <force-own-texture>0</force-own-texture>
            <global>0</global>
            <use-render-cells>0</use-render-cells>
            <blend-mode>0</blend-mode>
            <effect-fallback>0</effect-fallback>
            <instances>
                <instance type="TiledBackground5" uid="128">
                    <properties>
                        <initial-visibility>Visible</initial-visibility>
                        <hotspot>Top-left</hotspot>
                    </properties>
                    <blend-mode>0</blend-mode>
                    <effect-fallback>0</effect-fallback>
                    <world>
                        <x>28</x>
                        <y>-8</y>
                        <z>0</z>
                        <width>2880</width>
                        <height>574</height>
                        <depth>0</depth>
                        <hotspotX>0</hotspotX>
                        <hotspotY>0</hotspotY>
                        <angle>0</angle>
                        <opacity>1</opacity>
                    </world>
                </instance>
                <instance type="Sprite4" uid="129">
                    <properties>
                        <initial-visibility>Visible</initial-visibility>
                        <initial-animation>Default</initial-animation>
                        <initial-frame>0</initial-frame>
                        <collisions>Enabled</collisions>
                    </properties>
                    <behavior-instances>
                        <behavior-instance type="Solid">
                            <properties>
                                <initial-state>Enabled</initial-state>
                            </properties>
                        </behavior-instance>
                    </behavior-instances>
                    <blend-mode>0</blend-mode>
                    <effect-fallback>0</effect-fallback>
                    <world>
                        <x>367</x>
                        <y>217</y>
                        <z>0</z>
                        <width>168</width>
                        <height>44</height>
                        <depth>0</depth>
                        <hotspotX>0.676923096</hotspotX>
                        <hotspotY>0.593220353</hotspotY>
                        <angle>0</angle>
                        <opacity>1</opacity>
                    </world>
                </instance>
                <instance type="Sprite4" uid="130">
                    <properties>
                        <initial-visibility>Visible</initial-visibility>
                        <initial-animation>Default</initial-animation>
                        <initial-frame>0</initial-frame>
                        <collisions>Enabled</collisions>
                    </properties>
                    <behavior-instances>
                        <behavior-instance type="Solid">
                            <properties>
                                <initial-state>Enabled</initial-state>
                            </properties>
                        </behavior-instance>
                    </behavior-instances>
                    <blend-mode>0</blend-mode>
                    <effect-fallback>0</effect-fallback>
                    <world>
                        <x>790</x>
                        <y>204</y>
                        <z>0</z>
                        <width>168</width>
                        <height>44</height>
                        <depth>0</depth>
                        <hotspotX>0.676923096</hotspotX>
                        <hotspotY>0.593220353</hotspotY>
                        <angle>0</angle>
                        <opacity>1</opacity>
                    </world>
                </instance>
                <instance type="Sprite4" uid="131">
                    <properties>
                        <initial-visibility>Visible</initial-visibility>
                        <initial-animation>Default</initial-animation>
                        <initial-frame>0</initial-frame>
                        <collisions>Enabled</collisions>
                    </properties>
                    <behavior-instances>
                        <behavior-instance type="Solid">
                            <properties>
                                <initial-state>Enabled</initial-state>
                            </properties>
                        </behavior-instance>
                    </behavior-instances>
                    <blend-mode>0</blend-mode>
                    <effect-fallback>0</effect-fallback>
                    <world>
                        <x>580</x>
                        <y>313</y>
                        <z>0</z>
                        <width>168</width>
                        <height>44</height>
                        <depth>0</depth>
                        <hotspotX>0.676923096</hotspotX>
                        <hotspotY>0.593220353</hotspotY>
                        <angle>0</angle>
                        <opacity>1</opacity>
                    </world>
                </instance>
                <instance type="Sprite4" uid="132">
                    <properties>
                        <initial-visibility>Visible</initial-visibility>
                        <initial-animation>Default</initial-animation>
                        <initial-frame>0</initial-frame>
                        <collisions>Enabled</collisions>
                    </properties>
                    <behavior-instances>
                        <behavior-instance type="Solid">
                            <properties>
                                <initial-state>Enabled</initial-state>
                            </properties>
                        </behavior-instance>
                    </behavior-instances>
                    <blend-mode>0</blend-mode>
                    <effect-fallback>0</effect-fallback>
                    <world>
                        <x>1346</x>
                        <y>191</y>
                        <z>0</z>
                        <width>168</width>
                        <height>44</height>
                        <depth>0</depth>
                        <hotspotX>0.676923096</hotspotX>
                        <hotspotY>0.593220353</hotspotY>
                        <angle>0</angle>
                        <opacity>1</opacity>
                    </world>
                </instance>
                <instance type="Sprite4" uid="133">
                    <properties>
                        <initial-visibility>Visible</initial-visibility>
                        <initial-animation>Default</initial-animation>
                        <initial-frame>0</initial-frame>
                        <collisions>Enabled</collisions>
                    </properties>
                    <behavior-instances>
                        <behavior-instance type="Solid">
                            <properties>
                                <initial-state>Enabled</initial-state>
                            </properties>
                        </behavior-instance>
                    </behavior-instances>
                    <blend-mode>0</blend-mode>
                    <effect-fallback>0</effect-fallback>
                    <world>
                        <x>1544</x>
                        <y>355</y>
                        <z>0</z>
                        <width>168</width>
                        <height>44</height>
                        <depth>0</depth>
                        <hotspotX>0.676923096</hotspotX>
                        <hotspotY>0.593220353</hotspotY>
                        <angle>0</angle>
                        <opacity>1</opacity>
                    </world>
                </instance>
                <instance type="Sprite4" uid="134">
                    <properties>
                        <initial-visibility>Visible</initial-visibility>
                        <initial-animation>Default</initial-animation>
                        <initial-frame>0</initial-frame>
                        <collisions>Enabled</collisions>
                    </properties>
                    <behavior-instances>
                        <behavior-instance type="Solid">
                            <properties>
                                <initial-state>Enabled</initial-state>
                            </properties>
                        </behavior-instance>
                    </behavior-instances>
                    <blend-mode>0</blend-mode>
                    <effect-fallback>0</effect-fallback>
                    <world>
                        <x>1907</x>
                        <y>209</y>
                        <z>0</z>
                        <width>168</width>
                        <height>44</height>
                        <depth>0</depth>
                        <hotspotX>0.676923096</hotspotX>
                        <hotspotY>0.593220353</hotspotY>
                        <angle>0</angle>
                        <opacity>1</opacity>
                    </world>
                </instance>
                <instance type="Sprite4" uid="135">
                    <properties>
                        <initial-visibility>Visible</initial-visibility>
                        <initial-animation>Default</initial-animation>
                        <initial-frame>0</initial-frame>
                        <collisions>Enabled</collisions>
                    </properties>
                    <behavior-instances>
                        <behavior-instance type="Solid">
                            <properties>
                                <initial-state>Enabled</initial-state>
                            </properties>
                        </behavior-instance>
                    </behavior-instances>
                    <blend-mode>0</blend-mode>
                    <effect-fallback>0</effect-fallback>
                    <world>
                        <x>2354</x>
                        <y>202</y>
                        <z>0</z>
                        <width>168</width>
                        <height>44</height>
                        <depth>0</depth>
                        <hotspotX>0.676923096</hotspotX>
                        <hotspotY>0.593220353</hotspotY>
                        <angle>0</angle>
                        <opacity>1</opacity>
                    </world>
                </instance>
                <instance type="Sprite4" uid="136">
                    <properties>
                        <initial-visibility>Visible</initial-visibility>
                        <initial-animation>Default</initial-animation>
                        <initial-frame>0</initial-frame>
                        <collisions>Enabled</collisions>
                    </properties>
                    <behavior-instances>
                        <behavior-instance type="Solid">
                            <properties>
                                <initial-state>Enabled</initial-state>
                            </properties>
                        </behavior-instance>
                    </behavior-instances>
                    <blend-mode>0</blend-mode>
                    <effect-fallback>0</effect-fallback>
                    <world>
                        <x>2768</x>
                        <y>199</y>
                        <z>0</z>
                        <width>168</width>
                        <height>44</height>
                        <depth>0</depth>
                        <hotspotX>0.676923096</hotspotX>
                        <hotspotY>0.593220353</hotspotY>
                        <angle>0</angle>
                        <opacity>1</opacity>
                    </world>
                </instance>
                <instance type="Plat" uid="137">
                    <properties>
                        <initial-visibility>Visible</initial-visibility>
                        <initial-animation>Default</initial-animation>
                        <initial-frame>0</initial-frame>
                        <collisions>Enabled</collisions>
                    </properties>
                    <behavior-instances>
                        <behavior-instance type="Sine">
                            <properties>
                                <active-on-start>Yes</active-on-start>
                                <movement>Vertical</movement>
                                <wave>Sine</wave>
                                <period>7</period>
                                <period-random>0</period-random>
                                <period-offset>0</period-offset>
                                <period-offset-random>0</period-offset-random>
                                <magnitude>300</magnitude>
                                <magnitude-random>0</magnitude-random>
                            </properties>
                        </behavior-instance>
                        <behavior-instance type="Jumpthru">
                            <properties>
                                <initial-state>Enabled</initial-state>
                            </properties>
                        </behavior-instance>
                    </behavior-instances>
                    <blend-mode>0</blend-mode>
                    <effect-fallback>0</effect-fallback>
                    <world>
                        <x>201</x>
                        <y>182</y>
                        <z>0</z>
                        <width>139</width>
                        <height>20</height>
                        <depth>0</depth>
                        <hotspotX>0.676923096</hotspotX>
                        <hotspotY>0.593220353</hotspotY>
                        <angle>0</angle>
                        <opacity>1</opacity>
                    </world>
                </instance>
                <instance type="f" uid="138">
                    <properties>
                        <initial-visibility>Visible</initial-visibility>
                        <initial-animation>Default</initial-animation>
                        <initial-frame>0</initial-frame>
                        <collisions>Enabled</collisions>
                    </properties>
                    <behavior-instances>
                        <behavior-instance type="Sine">
                            <properties>
                                <active-on-start>Yes</active-on-start>
                                <movement>Horizontal</movement>
                                <wave>Sine</wave>
                                <period>4</period>
                                <period-random>0</period-random>
                                <period-offset>0</period-offset>
                                <period-offset-random>0</period-offset-random>
                                <magnitude>50</magnitude>
                                <magnitude-random>0</magnitude-random>
                            </properties>
                        </behavior-instance>
                    </behavior-instances>
                    <blend-mode>0</blend-mode>
                    <effect-fallback>0</effect-fallback>
                    <world>
                        <x>2200</x>
                        <y>368</y>
                        <z>0</z>
                        <width>148</width>
                        <height>30</height>
                        <depth>0</depth>
                        <hotspotX>0.676923096</hotspotX>
                        <hotspotY>0.593220353</hotspotY>
                        <angle>0</angle>
                        <opacity>1</opacity>
                    </world>
                </instance>
                <instance type="f" uid="139">
                    <properties>
                        <initial-visibility>Visible</initial-visibility>
                        <initial-animation>Default</initial-animation>
                        <initial-frame>0</initial-frame>
                        <collisions>Enabled</collisions>
                    </properties>
                    <behavior-instances>
                        <behavior-instance type="Sine">
                            <properties>
                                <active-on-start>Yes</active-on-start>
                                <movement>Horizontal</movement>
                                <wave>Sine</wave>
                                <period>4</period>
                                <period-random>0</period-random>
                                <period-offset>0</period-offset>
                                <period-offset-random>0</period-offset-random>
                                <magnitude>50</magnitude>
                                <magnitude-random>0</magnitude-random>
                            </properties>
                        </behavior-instance>
                    </behavior-instances>
                    <blend-mode>0</blend-mode>
                    <effect-fallback>0</effect-fallback>
                    <world>
                        <x>2547</x>
                        <y>362</y>
                        <z>0</z>
                        <width>148</width>
                        <height>30</height>
                        <depth>0</depth>
                        <hotspotX>0.676923096</hotspotX>
                        <hotspotY>0.593220353</hotspotY>
                        <angle>0</angle>
                        <opacity>1</opacity>
                    </world>
                </instance>
                <instance type="LenhadorDesenho" uid="153">
                    <properties>
                        <initial-visibility>Visible</initial-visibility>
                        <initial-animation>Default</initial-animation>
                        <initial-frame>0</initial-frame>
                        <collisions>Enabled</collisions>
                    </properties>
                    <instance-variables>
                        <Mover>0</Mover>
                    </instance-variables>
                    <behavior-instances>
                        <behavior-instance type="Sine">
                            <properties>
                                <active-on-start>Yes</active-on-start>
                                <movement>Horizontal</movement>
                                <wave>Sine</wave>
                                <period>4</period>
                                <period-random>0</period-random>
                                <period-offset>0</period-offset>
                                <period-offset-random>0</period-offset-random>
                                <magnitude>50</magnitude>
                                <magnitude-random>0</magnitude-random>
                            </properties>
                        </behavior-instance>
                    </behavior-instances>
                    <blend-mode>0</blend-mode>
                    <effect-fallback>0</effect-fallback>
                    <world>
                        <x>1398</x>
                        <y>133</y>
                        <z>0</z>
                        <width>130</width>
                        <height>135</height>
                        <depth>0</depth>
                        <hotspotX>0.505882382</hotspotX>
                        <hotspotY>0.5</hotspotY>
                        <angle>0</angle>
                        <opacity>1</opacity>
                    </world>
                </instance>
                <instance type="LenhadorDesenho" uid="154">
                    <properties>
                        <initial-visibility>Visible</initial-visibility>
                        <initial-animation>Default</initial-animation>
                        <initial-frame>0</initial-frame>
                        <collisions>Enabled</collisions>
                    </properties>
                    <instance-variables>
                        <Mover>0</Mover>
                    </instance-variables>
                    <behavior-instances>
                        <behavior-instance type="Sine">
                            <properties>
                                <active-on-start>Yes</active-on-start>
                                <movement>Horizontal</movement>
                                <wave>Sine</wave>
                                <period>4</period>
                                <period-random>0</period-random>
                                <period-offset>0</period-offset>
                                <period-offset-random>0</period-offset-random>
                                <magnitude>50</magnitude>
                                <magnitude-random>0</magnitude-random>
                            </properties>
                        </behavior-instance>
                    </behavior-instances>
                    <blend-mode>0</blend-mode>
                    <effect-fallback>0</effect-fallback>
                    <world>
                        <x>1471</x>
                        <y>297</y>
                        <z>0</z>
                        <width>130</width>
                        <height>135</height>
                        <depth>0</depth>
                        <hotspotX>0.505882382</hotspotX>
                        <hotspotY>0.5</hotspotY>
                        <angle>0</angle>
                        <opacity>1</opacity>
                    </world>
                </instance>
                <instance type="LenhadorDesenho" uid="155">
                    <properties>
                        <initial-visibility>Visible</initial-visibility>
                        <initial-animation>Default</initial-animation>
                        <initial-frame>0</initial-frame>
                        <collisions>Enabled</collisions>
                    </properties>
                    <instance-variables>
                        <Mover>0</Mover>
                    </instance-variables>
                    <behavior-instances>
                        <behavior-instance type="Sine">
                            <properties>
                                <active-on-start>Yes</active-on-start>
                                <movement>Horizontal</movement>
                                <wave>Sine</wave>
                                <period>4</period>
                                <period-random>0</period-random>
                                <period-offset>0</period-offset>
                                <period-offset-random>0</period-offset-random>
                                <magnitude>50</magnitude>
                                <magnitude-random>0</magnitude-random>
                            </properties>
                        </behavior-instance>
                    </behavior-instances>
                    <blend-mode>0</blend-mode>
                    <effect-fallback>0</effect-fallback>
                    <world>
                        <x>2225</x>
                        <y>321</y>
                        <z>0</z>
                        <width>130</width>
                        <height>135</height>
                        <depth>0</depth>
                        <hotspotX>0.505882382</hotspotX>
                        <hotspotY>0.5</hotspotY>
                        <angle>0</angle>
                        <opacity>1</opacity>
                    </world>
                </instance>
                <instance type="LenhadorDesenho" uid="156">
                    <properties>
                        <initial-visibility>Visible</initial-visibility>
                        <initial-animation>Default</initial-animation>
                        <initial-frame>0</initial-frame>
                        <collisions>Enabled</collisions>
                    </properties>
                    <instance-variables>
                        <Mover>0</Mover>
                    </instance-variables>
                    <behavior-instances>
                        <behavior-instance type="Sine">
                            <properties>
                                <active-on-start>Yes</active-on-start>
                                <movement>Horizontal</movement>
                                <wave>Sine</wave>
                                <period>4</period>
                                <period-random>0</period-random>
                                <period-offset>0</period-offset>
                                <period-offset-random>0</period-offset-random>
                                <magnitude>50</magnitude>
                                <magnitude-random>0</magnitude-random>
                            </properties>
                        </behavior-instance>
                    </behavior-instances>
                    <blend-mode>0</blend-mode>
                    <effect-fallback>0</effect-fallback>
                    <world>
                        <x>2386</x>
                        <y>463</y>
                        <z>0</z>
                        <width>130</width>
                        <height>135</height>
                        <depth>0</depth>
                        <hotspotX>0.505882382</hotspotX>
                        <hotspotY>0.5</hotspotY>
                        <angle>0</angle>
                        <opacity>1</opacity>
                    </world>
                </instance>
                <instance type="LenhadorDesenho" uid="157">
                    <properties>
                        <initial-visibility>Visible</initial-visibility>
                        <initial-animation>Default</initial-animation>
                        <initial-frame>0</initial-frame>
                        <collisions>Enabled</collisions>
                    </properties>
                    <instance-variables>
                        <Mover>0</Mover>
                    </instance-variables>
                    <behavior-instances>
                        <behavior-instance type="Sine">
                            <properties>
                                <active-on-start>Yes</active-on-start>
                                <movement>Horizontal</movement>
                                <wave>Sine</wave>
                                <period>4</period>
                                <period-random>0</period-random>
                                <period-offset>0</period-offset>
                                <period-offset-random>0</period-offset-random>
                                <magnitude>50</magnitude>
                                <magnitude-random>0</magnitude-random>
                            </properties>
                        </behavior-instance>
                    </behavior-instances>
                    <blend-mode>0</blend-mode>
                    <effect-fallback>0</effect-fallback>
                    <world>
                        <x>2617</x>
                        <y>465</y>
                        <z>0</z>
                        <width>130</width>
                        <height>135</height>
                        <depth>0</depth>
                        <hotspotX>0.505882382</hotspotX>
                        <hotspotY>0.5</hotspotY>
                        <angle>0</angle>
                        <opacity>1</opacity>
                    </world>
                </instance>
                <instance type="LenhadorDesenho" uid="158">
                    <properties>
                        <initial-visibility>Visible</initial-visibility>
                        <initial-animation>Default</initial-animation>
                        <initial-frame>0</initial-frame>
                        <collisions>Enabled</collisions>
                    </properties>
                    <instance-variables>
                        <Mover>0</Mover>
                    </instance-variables>
                    <behavior-instances>
                        <behavior-instance type="Sine">
                            <properties>
                                <active-on-start>Yes</active-on-start>
                                <movement>Horizontal</movement>
                                <wave>Sine</wave>
                                <period>4</period>
                                <period-random>0</period-random>
                                <period-offset>0</period-offset>
                                <period-offset-random>0</period-offset-random>
                                <magnitude>50</magnitude>
                                <magnitude-random>0</magnitude-random>
                            </properties>
                        </behavior-instance>
                    </behavior-instances>
                    <blend-mode>0</blend-mode>
                    <effect-fallback>0</effect-fallback>
                    <world>
                        <x>1934</x>
                        <y>326</y>
                        <z>0</z>
                        <width>130</width>
                        <height>135</height>
                        <depth>0</depth>
                        <hotspotX>0.505882382</hotspotX>
                        <hotspotY>0.5</hotspotY>
                        <angle>0</angle>
                        <opacity>1</opacity>
                    </world>
                </instance>
                <instance type="LenhadorDesenho" uid="159">
                    <properties>
                        <initial-visibility>Visible</initial-visibility>
                        <initial-animation>Default</initial-animation>
                        <initial-frame>0</initial-frame>
                        <collisions>Enabled</collisions>
                    </properties>
                    <instance-variables>
                        <Mover>0</Mover>
                    </instance-variables>
                    <behavior-instances>
                        <behavior-instance type="Sine">
                            <properties>
                                <active-on-start>Yes</active-on-start>
                                <movement>Horizontal</movement>
                                <wave>Sine</wave>
                                <period>4</period>
                                <period-random>0</period-random>
                                <period-offset>0</period-offset>
                                <period-offset-random>0</period-offset-random>
                                <magnitude>50</magnitude>
                                <magnitude-random>0</magnitude-random>
                            </properties>
                        </behavior-instance>
                    </behavior-instances>
                    <blend-mode>0</blend-mode>
                    <effect-fallback>0</effect-fallback>
                    <world>
                        <x>2683</x>
                        <y>148</y>
                        <z>0</z>
                        <width>130</width>
                        <height>135</height>
                        <depth>0</depth>
                        <hotspotX>0.505882382</hotspotX>
                        <hotspotY>0.5</hotspotY>
                        <angle>0</angle>
                        <opacity>1</opacity>
                    </world>
                </instance>
                <instance type="LenhadorDesenho" uid="160">
                    <properties>
                        <initial-visibility>Visible</initial-visibility>
                        <initial-animation>Default</initial-animation>
                        <initial-frame>0</initial-frame>
                        <collisions>Enabled</collisions>
                    </properties>
                    <instance-variables>
                        <Mover>0</Mover>
                    </instance-variables>
                    <behavior-instances>
                        <behavior-instance type="Sine">
                            <properties>
                                <active-on-start>Yes</active-on-start>
                                <movement>Horizontal</movement>
                                <wave>Sine</wave>
                                <period>4</period>
                                <period-random>0</period-random>
                                <period-offset>0</period-offset>
                                <period-offset-random>0</period-offset-random>
                                <magnitude>50</magnitude>
                                <magnitude-random>0</magnitude-random>
                            </properties>
                        </behavior-instance>
                    </behavior-instances>
                    <blend-mode>0</blend-mode>
                    <effect-fallback>0</effect-fallback>
                    <world>
                        <x>802</x>
                        <y>355</y>
                        <z>0</z>
                        <width>130</width>
                        <height>135</height>
                        <depth>0</depth>
                        <hotspotX>0.505882382</hotspotX>
                        <hotspotY>0.5</hotspotY>
                        <angle>0</angle>
                        <opacity>1</opacity>
                    </world>
                </instance>
                <instance type="TiledBackground7" uid="161">
                    <properties>
                        <initial-visibility>Visible</initial-visibility>
                        <hotspot>Top-left</hotspot>
                    </properties>
                    <behavior-instances>
                        <behavior-instance type="Solid">
                            <properties>
                                <initial-state>Enabled</initial-state>
                            </properties>
                        </behavior-instance>
                    </behavior-instances>
                    <blend-mode>0</blend-mode>
                    <effect-fallback>0</effect-fallback>
                    <world>
                        <x>-9</x>
                        <y>-8</y>
                        <z>0</z>
                        <width>2883</width>
                        <height>97</height>
                        <depth>0</depth>
                        <hotspotX>0</hotspotX>
                        <hotspotY>0</hotspotY>
                        <angle>0</angle>
                        <opacity>1</opacity>
                    </world>
                </instance>
                <instance type="TiledBackground7" uid="162">
                    <properties>
                        <initial-visibility>Visible</initial-visibility>
                        <hotspot>Top-left</hotspot>
                    </properties>
                    <behavior-instances>
                        <behavior-instance type="Solid">
                            <properties>
                                <initial-state>Enabled</initial-state>
                            </properties>
                        </behavior-instance>
                    </behavior-instances>
                    <blend-mode>0</blend-mode>
                    <effect-fallback>0</effect-fallback>
                    <world>
                        <x>912</x>
                        <y>343</y>
                        <z>0</z>
                        <width>192</width>
                        <height>192</height>
                        <depth>0</depth>
                        <hotspotX>0</hotspotX>
                        <hotspotY>0</hotspotY>
                        <angle>0</angle>
                        <opacity>1</opacity>
                    </world>
                </instance>
                <instance type="TiledBackground7" uid="163">
                    <properties>
                        <initial-visibility>Visible</initial-visibility>
                        <hotspot>Top-left</hotspot>
                    </properties>
                    <behavior-instances>
                        <behavior-instance type="Solid">
                            <properties>
                                <initial-state>Enabled</initial-state>
                            </properties>
                        </behavior-instance>
                    </behavior-instances>
                    <blend-mode>0</blend-mode>
                    <effect-fallback>0</effect-fallback>
                    <world>
                        <x>-3</x>
                        <y>25</y>
                        <z>0</z>
                        <width>91</width>
                        <height>554</height>
                        <depth>0</depth>
                        <hotspotX>0</hotspotX>
                        <hotspotY>0</hotspotY>
                        <angle>0</angle>
                        <opacity>1</opacity>
                    </world>
                </instance>
                <instance type="TiledBackground7" uid="164">
                    <properties>
                        <initial-visibility>Visible</initial-visibility>
                        <hotspot>Top-left</hotspot>
                    </properties>
                    <behavior-instances>
                        <behavior-instance type="Solid">
                            <properties>
                                <initial-state>Enabled</initial-state>
                            </properties>
                        </behavior-instance>
                    </behavior-instances>
                    <blend-mode>0</blend-mode>
                    <effect-fallback>0</effect-fallback>
                    <world>
                        <x>1504</x>
                        <y>47</y>
                        <z>0</z>
                        <width>278</width>
                        <height>139</height>
                        <depth>0</depth>
                        <hotspotX>0</hotspotX>
                        <hotspotY>0</hotspotY>
                        <angle>0</angle>
                        <opacity>1</opacity>
                    </world>
                </instance>
                <instance type="TiledBackground7" uid="165">
                    <properties>
                        <initial-visibility>Visible</initial-visibility>
                        <hotspot>Top-left</hotspot>
                    </properties>
                    <behavior-instances>
                        <behavior-instance type="Solid">
                            <properties>
                                <initial-state>Enabled</initial-state>
                            </properties>
                        </behavior-instance>
                    </behavior-instances>
                    <blend-mode>0</blend-mode>
                    <effect-fallback>0</effect-fallback>
                    <world>
                        <x>-2</x>
                        <y>498</y>
                        <z>0</z>
                        <width>2903</width>
                        <height>74</height>
                        <depth>0</depth>
                        <hotspotX>0</hotspotX>
                        <hotspotY>0</hotspotY>
                        <angle>0</angle>
                        <opacity>1</opacity>
                    </world>
                </instance>
                <instance type="TiledBackground7" uid="166">
                    <properties>
                        <initial-visibility>Visible</initial-visibility>
                        <hotspot>Top-left</hotspot>
                    </properties>
                    <behavior-instances>
                        <behavior-instance type="Solid">
                            <properties>
                                <initial-state>Enabled</initial-state>
                            </properties>
                        </behavior-instance>
                    </behavior-instances>
                    <blend-mode>0</blend-mode>
                    <effect-fallback>0</effect-fallback>
                    <world>
                        <x>461</x>
                        <y>14</y>
                        <z>0</z>
                        <width>192</width>
                        <height>152</height>
                        <depth>0</depth>
                        <hotspotX>0</hotspotX>
                        <hotspotY>0</hotspotY>
                        <angle>0</angle>
                        <opacity>1</opacity>
                    </world>
                </instance>
                <instance type="TiledBackground7" uid="167">
                    <properties>
                        <initial-visibility>Visible</initial-visibility>
                        <hotspot>Top-left</hotspot>
                    </properties>
                    <behavior-instances>
                        <behavior-instance type="Solid">
                            <properties>
                                <initial-state>Enabled</initial-state>
                            </properties>
                        </behavior-instance>
                    </behavior-instances>
                    <blend-mode>0</blend-mode>
                    <effect-fallback>0</effect-fallback>
                    <world>
                        <x>719</x>
                        <y>389</y>
                        <z>0</z>
                        <width>192</width>
                        <height>182</height>
                        <depth>0</depth>
                        <hotspotX>0</hotspotX>
                        <hotspotY>0</hotspotY>
                        <angle>0</angle>
                        <opacity>1</opacity>
                    </world>
                </instance>
                <instance type="TiledBackground7" uid="168">
                    <properties>
                        <initial-visibility>Visible</initial-visibility>
                        <hotspot>Top-left</hotspot>
                    </properties>
                    <behavior-instances>
                        <behavior-instance type="Solid">
                            <properties>
                                <initial-state>Enabled</initial-state>
                            </properties>
                        </behavior-instance>
                    </behavior-instances>
                    <blend-mode>0</blend-mode>
                    <effect-fallback>0</effect-fallback>
                    <world>
                        <x>1088</x>
                        <y>299</y>
                        <z>0</z>
                        <width>192</width>
                        <height>263</height>
                        <depth>0</depth>
                        <hotspotX>0</hotspotX>
                        <hotspotY>0</hotspotY>
                        <angle>0</angle>
                        <opacity>1</opacity>
                    </world>
                </instance>
                <instance type="TiledBackground7" uid="169">
                    <properties>
                        <initial-visibility>Visible</initial-visibility>
                        <hotspot>Top-left</hotspot>
                    </properties>
                    <behavior-instances>
                        <behavior-instance type="Solid">
                            <properties>
                                <initial-state>Enabled</initial-state>
                            </properties>
                        </behavior-instance>
                    </behavior-instances>
                    <blend-mode>0</blend-mode>
                    <effect-fallback>0</effect-fallback>
                    <world>
                        <x>1844</x>
                        <y>362</y>
                        <z>0</z>
                        <width>192</width>
                        <height>202</height>
                        <depth>0</depth>
                        <hotspotX>0</hotspotX>
                        <hotspotY>0</hotspotY>
                        <angle>0</angle>
                        <opacity>1</opacity>
                    </world>
                </instance>
                <instance type="Bloco" uid="186">
                    <properties>
                        <initial-visibility>Invisible</initial-visibility>
                        <initial-animation>Default</initial-animation>
                        <initial-frame>0</initial-frame>
                        <collisions>Enabled</collisions>
                    </properties>
                    <behavior-instances>
                        <behavior-instance type="ScrollTo">
                            <properties>
                                <initial-state>Enabled</initial-state>
                            </properties>
                        </behavior-instance>
                        <behavior-instance type="Platform">
                            <properties>
                                <max-speed>330</max-speed>
                                <acceleration>1500</acceleration>
                                <deceleration>1500</deceleration>
                                <jump-strength>650</jump-strength>
                                <gravity>1500</gravity>
                                <max-fall-speed>1000</max-fall-speed>
                                <double-jump>Disabled</double-jump>
                                <jump-sustain>0</jump-sustain>
                                <default-controls>Yes</default-controls>
                                <initial-state>Enabled</initial-state>
                            </properties>
                        </behavior-instance>
                        <behavior-instance type="BoundToLayout">
                            <properties>
                                <bound-by>Edge</bound-by>
                            </properties>
                        </behavior-instance>
                    </behavior-instances>
                    <blend-mode>0</blend-mode>
                    <effect-fallback>0</effect-fallback>
                    <world>
                        <x>174</x>
                        <y>424</y>
                        <z>0</z>
                        <width>54</width>
                        <height>89</height>
                        <depth>0</depth>
                        <hotspotX>0.5</hotspotX>
                        <hotspotY>0.5</hotspotY>
                        <angle>0</angle>
                        <opacity>1</opacity>
                    </world>
                </instance>
            </instances>
            <effects />
        </layer>
        <layer name="Hud" sid="251549582691081">
            <initially-visible>1</initially-visible>
            <background-color>255,255,255</background-color>
            <transparent>1</transparent>
            <parallax>
                <x>0</x>
                <y>0</y>
            </parallax>
            <zoom-rate>1</zoom-rate>
            <opacity>1</opacity>
            <force-own-texture>0</force-own-texture>
            <global>0</global>
            <use-render-cells>0</use-render-cells>
            <blend-mode>0</blend-mode>
            <effect-fallback>0</effect-fallback>
            <instances>
                <instance type="VidaVazia" uid="182">
                    <properties>
                        <initial-visibility>Visible</initial-visibility>
                        <initial-animation>Default</initial-animation>
                        <initial-frame>0</initial-frame>
                        <collisions>Enabled</collisions>
                    </properties>
                    <blend-mode>0</blend-mode>
                    <effect-fallback>0</effect-fallback>
                    <world>
                        <x>125</x>
                        <y>138</y>
                        <z>0</z>
                        <width>56.887191772</width>
                        <height>72.00214386</height>
                        <depth>0</depth>
                        <hotspotX>0.5</hotspotX>
                        <hotspotY>0.5</hotspotY>
                        <angle>0</angle>
                        <opacity>1</opacity>
                    </world>
                </instance>
                <instance type="Vida" uid="183">
                    <properties>
                        <initial-visibility>Visible</initial-visibility>
                        <initial-animation>Default</initial-animation>
                        <initial-frame>0</initial-frame>
                        <collisions>Enabled</collisions>
                    </properties>
                    <blend-mode>0</blend-mode>
                    <effect-fallback>0</effect-fallback>
                    <world>
                        <x>2318</x>
                        <y>-347</y>
                        <z>0</z>
                        <width>56.887191772</width>
                        <height>72.00214386</height>
                        <depth>0</depth>
                        <hotspotX>0.5</hotspotX>
                        <hotspotY>0.5</hotspotY>
                        <angle>0</angle>
                        <opacity>1</opacity>
                    </world>
                </instance>
                <instance type="VidaVazia" uid="184">
                    <properties>
                        <initial-visibility>Visible</initial-visibility>
                        <initial-animation>Default</initial-animation>
                        <initial-frame>0</initial-frame>
                        <collisions>Enabled</collisions>
                    </properties>
                    <blend-mode>0</blend-mode>
                    <effect-fallback>0</effect-fallback>
                    <world>
                        <x>177</x>
                        <y>141</y>
                        <z>0</z>
                        <width>56.887191772</width>
                        <height>72.00214386</height>
                        <depth>0</depth>
                        <hotspotX>0.5</hotspotX>
                        <hotspotY>0.5</hotspotY>
                        <angle>0</angle>
                        <opacity>1</opacity>
                    </world>
                </instance>
                <instance type="VidaVazia" uid="185">
                    <properties>
                        <initial-visibility>Visible</initial-visibility>
                        <initial-animation>Default</initial-animation>
                        <initial-frame>0</initial-frame>
                        <collisions>Enabled</collisions>
                    </properties>
                    <blend-mode>0</blend-mode>
                    <effect-fallback>0</effect-fallback>
                    <world>
                        <x>232</x>
                        <y>144</y>
                        <z>0</z>
                        <width>56.887191772</width>
                        <height>72.00214386</height>
                        <depth>0</depth>
                        <hotspotX>0.5</hotspotX>
                        <hotspotY>0.5</hotspotY>
                        <angle>0</angle>
                        <opacity>1</opacity>
                    </world>
                </instance>
            </instances>
            <effects />
        </layer>
        <layer name="Layer 1" sid="313027068844079">
            <initially-visible>1</initially-visible>
            <background-color>255,255,255</background-color>
            <transparent>1</transparent>
            <parallax>
                <x>1</x>
                <y>1</y>
            </parallax>
            <zoom-rate>1</zoom-rate>
            <opacity>1</opacity>
            <force-own-texture>0</force-own-texture>
            <global>0</global>
            <use-render-cells>0</use-render-cells>
            <blend-mode>0</blend-mode>
            <effect-fallback>0</effect-fallback>
            <instances>
                <instance type="SaciDesenho" uid="41">
                    <properties>
                        <initial-visibility>Visible</initial-visibility>
                        <initial-animation>curupira</initial-animation>
                        <initial-frame>0</initial-frame>
                        <collisions>Enabled</collisions>
                    </properties>
                    <instance-variables>
                        <Vida>3</Vida>
                    </instance-variables>
                    <behavior-instances>
                        <behavior-instance type="Pin" />
                    </behavior-instances>
                    <blend-mode>0</blend-mode>
                    <effect-fallback>0</effect-fallback>
                    <world>
                        <x>189</x>
                        <y>449</y>
                        <z>0</z>
                        <width>31.591398239</width>
                        <height>73.178878784</height>
                        <depth>0</depth>
                        <hotspotX>1.125</hotspotX>
                        <hotspotY>0.826086938</hotspotY>
                        <angle>0</angle>
                        <opacity>1</opacity>
                    </world>
                </instance>
            </instances>
            <effects />
        </layer>
    </layers>
    <nonworld-instances />
    <effects />
</c2layout>
